{
  "id": "fundamentals-objects",
  "title": "Object types",
  "description": "Define object types with objectRef and implement, and switch between the objectRef, class-backed, and builder-types styles.",
  "category": "core",
  "subcategory": "fundamentals",
  "difficulty": "beginner",
  "order": 2,
  "tags": ["objects", "objectRef"],
  "relatedDocs": ["/docs/fundamentals/objects"],
  "variants": [
    { "id": "object-refs", "title": "Object refs", "order": 1, "default": true },
    { "id": "classes", "title": "Classes", "order": 2 },
    { "id": "builder-types", "title": "Builder types", "order": 3 }
  ]
}
